{"L54aDsO7EgnbHvKC9Yah7g==":"mbr-810x1080.jpg","vcLZs8osCcoA27JbXpmQqg==":"mbr-1-810x1080.jpg","MaQSIh1p8UZVP2+e6MHFZg==":"01.jpg","3ubFYh2lIVEt/92HbTR3yg==":"05.jpg","WGDjefpuv5ubcogSAjqMyQ==":"02.jpg","6M/rCSTa4euWFRfSSZhd7A==":"bildschirmfoto%202017-11-10%20um%2017.28.42-880x1564.png","x188mC/qk8QFFfFVJWWWMQ==":"bildschirmfoto%202017-11-10%20um%2017.28.47-880x1567.png","y3zETLRvAD3/eMoBi//mIw==":"bildschirmfoto%202017-11-10%20um%2017.28.58-879x1566.png","53Ts6YUOWMWtgnZdwepyAg==":"ic_launcher_google_play-512x512.png","k8JdiE+vhYaFDpkA5wo5RA==":"logo123-1277x1277.jpg","QA93T3WRlkJLcnlLbmUUoA==":"logo123-1277x1277.png","SHI+t8cIDOLJ9ebYWdJ/Dw==":"app-icon-app-store-1024x1024.jpg","aGw+DtFKo/i0KFXbrf3TgA==":"app-icon-app-store-1-1024x1024.jpg","TcFSJnJjX09sODH2AnlKLQ==":"app-icon-app-store-2-1024x1024.jpg","UhfXEgIJkdDd/495Vb505w==":"app-icon-app-store-3-1024x1024.jpg","Bnw6jMBcAk+MlHTtRo73wA==":"app-icon-app-store-4-1024x1024.jpg","PahjB/xR2VKNWXL1lFbBbg==":"bildschirmfoto%202018-02-10%20um%2014.16.08-667x1211.png","5lPTgRExqLkGgKmyiZ1MaQ==":"lt01-674x1227.jpg","DUhXWrjjQUGriftcT6xzkg==":"lt02-674x1227.jpg","yrajAxlpauEtiMwMYrbjuQ==":"lt03-673x1226.jpg","z9+rLEV2mbNl2fP0yL6qaA==":"lt03-674x1227.jpg","zpTIta+oJGLhmNVTOVGexg==":"lt04-400x300.jpg","0gaFi1Lo2ED6GGLioGCEog==":"lt05-400x300.jpg","SPF3BjLWzHU1Rp0SfjY26g==":"lt06-400x300.jpg","fSZuHemrya2CGjsqw1idpw==":"lt07-400x300.jpg","+VIsz+hYlEVTYs3eyZApuw==":"lt09-400x300.jpg","Aita1Po6JKnkUL8/cPkFvA==":"lt10-400x300.jpg","TMiJnErMdvnjzDs6TPsjjA==":"group-748x762.png","PtaTUcxX5Oth8YNPlZdAEQ==":"mockup-2000x1500.png","jrNKDVClD09bx99d6sUP0Q==":"mockup1-2000x2000.png","UwkPz6bCZqL6O7MtSr82LA==":"mockup3-2000x2000.png","g4mie4KE8CK8/oNbPKTUSw==":"mockup5-2000x2044.png","bRah9iJZqDGT9JlmQ6UD6Q==":"mockup6-2000x2000.png","FEGzlJip6wBz/Piz896ZGQ==":"start-2000x1999.png","SR4KCpIKfNIwKvQvj+7j4g==":"mockup01-906x1633.png","bufK8cW0liw0WZ/vvrCgAw==":"appscreen01-884x1621.png","M0j5GmCpHsl9v/JmA9CBKQ==":"appscreen02-884x1621.png","ZzaYJH0wHXVEAcsZ5PFpiw==":"appscreen03-883x1621.png","XbQZm9QHzDU3yi2TcpPM8A==":"search-2-64x64.png","V/GmUwcvs6zwdbQR+JYjVA==":"search-3-512x512.png","XB62IFDkmPysH+U+2jhuHw==":"search-3-256x256.png","qtoZB/MsVtGoyR+ovfzvZw==":"search-2-128x128.png","32WU0S9MlpSXM5MLRfhtAQ==":"mockup01-2000x2000.png","xjRE9P80oieG+aQTF29ypg==":"iiiiiii-1000x1000.png","VNocGTUk0dRVSeKM6zDglQ==":"mockup-3300x2475.png","wLSvuUnbMteoqmCVET4QDg==":"mockup-1-3300x2475.png","ajuP1ZsQwnTNEqog4WfSBA==":"mockup-2511x2475.png","dOQXUQV/U/TmLqymuNmqpg==":"mockup-2-3300x2475.png","r6yK02UhzEWSbxvUFZVB9w==":"background3.jpg","xQQ7z9RgaRSma6xryMW7Mg==":"mockup03-2000x1918.png","s5H71ZvDBizJKASnZeaQUw==":"mockup06-2000x2001.png","ve1YSZ8wwPYj61EKZzC8Hw==":"mockup06-2000x1905.png","2M6EDZDEZk8OA7g1CmpCug==":"mockup06-2000x2000.png","jNqdoWiNg568UHMDT5MLXg==":"mockup%20kopie%203-1000x750.png","CX1LDqnynT9sascjtybRmA==":"mockup%20kopie%204-1000x750.png","TFr6TPxbTzAmg59gdDjFKA==":"mockup%20kopie%205-1000x750.png","VamuAJwWViY9PKz7/lTrZw==":"mockup%20kopie%206-1000x750.png","tdppB4fVvxlUtLjkt7hTfQ==":"mockup%20kopie%207-500x375.png","eSXdaH2nhEdHn6/PSlJhYg==":"mockup-500x375.png","37NpovyPBErjgAi4McvTpA==":"mockupfooter-500x375.png","R3jxgeuIHTu+ytJBaDqDUQ==":"mockup01-1-2000x2000.png","TMAipToc1aQFz6I0ZlVTEQ==":"mockup-3840x2880.png","pfU/s+oZv6eBX33PLgg4KA==":"mockup-1-3840x2880.png","PVDVOomgfC9e1q/mCtmVew==":"mockup-2700x2700.png","3OOtKbb4Do78xLDQ32Q3/w==":"mockup-1-2700x2700.png","ezN+Eg6cIr3MK31ZQLSHJA==":"mockup-2-2700x2700.png","8Xtl9HpsiNrxWl9TjPGjcA==":"mockup-3-2700x2700.png","2MZqsWYxVQ+NwBukJ1elyA==":"mockup-4-2700x2700.png","K9WtRIwWWLo1L3IR5aGvtg==":"mockup-5-2700x2700.png"}